nexus/__init__.py
nexus/app.py
nexus/config.py
nexus/container.py
nexus/logger.py
nexus/models.py
nexus/state.py
nexus/style.tcss
nexus/tools.toml
nexus/screens/__init__.py
nexus/screens/create_project.py
nexus/screens/error.py
nexus/screens/help.py
nexus/screens/project_picker.py
nexus/screens/theme_picker.py
nexus/screens/tool_selector.py
nexus/services/__init__.py
nexus/services/executor.py
nexus/services/scanner.py
nexus/widgets/__init__.py
nexus/widgets/tool_list_item.py
nexus_tui-0.1.14.dist-info/METADATA
nexus_tui-0.1.14.dist-info/WHEEL
nexus_tui-0.1.14.dist-info/entry_points.txt
nexus_tui-0.1.14.dist-info/licenses/LICENSE
nexus_tui-0.1.14.dist-info/RECORD
