Metadata-Version: 2.4
Name: nexus-tui
Version: 0.1.14
Summary: A TUI orchestrator to manage your installed terminal tools—access everything through a single command
License-File: LICENSE
Requires-Python: >=3.12
Requires-Dist: platformdirs>=4.0.0
Requires-Dist: pydantic>=2.12.5
Requires-Dist: structlog>=24.1.0
Requires-Dist: textual>=0.86.0
Requires-Dist: thefuzz>=0.20.0
